lightdash/__init__.py
lightdash/client.py
lightdash/dimensions.py
lightdash/metrics.py
lightdash/models.py
lightdash/query.py
lightdash/types.py
lightdash-0.3.0.dist-info/licenses/LICENSE
lightdash-0.3.0.dist-info/METADATA
lightdash-0.3.0.dist-info/WHEEL
lightdash-0.3.0.dist-info/top_level.txt
lightdash-0.3.0.dist-info/RECORD
