Metadata-Version: 2.4
Name: lightdash
Version: 0.3.0
Summary: Query metrics from Lightdash
Author-email: Oliver Laslett <oliver@lightdash.com>
License: MIT
Requires-Python: >=3.9
License-File: LICENSE
Requires-Dist: httpx>=0.25.0
Provides-Extra: dev
Requires-Dist: pytest>=7.0.0; extra == "dev"
Requires-Dist: jupyter>=1.0.0; extra == "dev"
Requires-Dist: ipykernel>=6.0.0; extra == "dev"
Requires-Dist: pandas>=2.0.0; extra == "dev"
Requires-Dist: polars>=1.22.0; extra == "dev"
Dynamic: license-file
